cisco_config_parser/__init__.py
cisco_config_parser/cisco_config_parser.py
cisco_config_parser/setup.py
cisco_config_parser/global_search/__init__.py
cisco_config_parser/global_search/global_obj.py
cisco_config_parser/global_search/global_parser.py
cisco_config_parser/global_search/global_separator.py
cisco_config_parser/global_search/ios/__init__.py
cisco_config_parser/global_search/nxos/__init__.py
cisco_config_parser/global_search/xr/__init__.py
cisco_config_parser/helper/__init__.py
cisco_config_parser/helper/help.py
cisco_config_parser/helper/helper.py
cisco_config_parser/layer2_interface/__init__.py
cisco_config_parser/layer2_interface/l2_interface_obj.py
cisco_config_parser/layer2_interface/l2_interface_parser.py
cisco_config_parser/layer2_interface/l2_interface_separator.py
cisco_config_parser/layer2_interface/l2_section_parser.py
cisco_config_parser/layer3_interface/__init__.py
cisco_config_parser/layer3_interface/l3_interface_obj.py
cisco_config_parser/layer3_interface/l3_interface_parser.py
cisco_config_parser/layer3_interface/l3_interface_separator.py
cisco_config_parser/layer3_interface/l3_section_parser.py
cisco_config_parser/old_version/__init__.py
cisco_config_parser/old_version/exceptions.py
cisco_config_parser/old_version/obj.py
cisco_config_parser/old_version/old_parse.py
cisco_config_parser/old_version/ssh.py
cisco_config_parser/old_version/utils.py
cisco_config_parser/parent_child/__init__.py
cisco_config_parser/parent_child/parent_child_obj.py
cisco_config_parser/parent_child/parent_child_parser.py
cisco_config_parser/parent_child/parent_child_separator.py
cisco_config_parser/parser/__init__.py
cisco_config_parser/parser/parser.py
cisco_config_parser/parser_regex/__init__.py
cisco_config_parser/parser_regex/common_regex.py
cisco_config_parser/parser_regex/ios_regex.py
cisco_config_parser/parser_regex/nxos_regex.py
cisco_config_parser/routing_protocol/__init__.py
cisco_config_parser/routing_protocol/ios/__init__.py
cisco_config_parser-2.3.0.dist-info/METADATA
cisco_config_parser-2.3.0.dist-info/WHEEL
cisco_config_parser-2.3.0.dist-info/top_level.txt
cisco_config_parser-2.3.0.dist-info/RECORD
