Metadata-Version: 2.1
Name: cisco_config_parser
Version: 2.3.0
Summary: This library is used for Network Automation involving Cisco Routers and Switch. It will parse Cisco IOS, IOS-XE, IOS-XR, and NXOS configuration file into objects and/or json format
Home-page: https://github.com/arezazadeh/cisco_config_parser
Author: Ahmad Rezazadeh
Author-email: ahmad@klevernet.io
License: MIT License
